gb2260/__init__.py
gb2260/_compat.py
gb2260/data.py
gb2260/division.py
GB2260-0.4.1.dist-info/DESCRIPTION.rst
GB2260-0.4.1.dist-info/METADATA
GB2260-0.4.1.dist-info/metadata.json
GB2260-0.4.1.dist-info/RECORD
GB2260-0.4.1.dist-info/top_level.txt
GB2260-0.4.1.dist-info/WHEEL
